llm_workflow/__init__.py
llm_workflow/agents.py
llm_workflow/base.py
llm_workflow/compare.py
llm_workflow/exceptions.py
llm_workflow/hugging_face.py
llm_workflow/indexes.py
llm_workflow/internal_utilities.py
llm_workflow/llama_cpp_endpoint.py
llm_workflow/memory.py
llm_workflow/message_formatters.py
llm_workflow/openai.py
llm_workflow/prompt_templates.py
llm_workflow/resources.py
llm_workflow/utilities.py
tests/__init__.py
tests/conftest.py
tests/test_agents.py
tests/test_base.py
tests/test_compare.py
tests/test_history.py
tests/test_hugging_face.py
tests/test_indexes.py
tests/test_llama_cpp_server.py
tests/test_message_formatters.py
tests/test_openai.py
tests/test_prompt_templates.py
tests/test_records.py
tests/test_session.py
tests/test_utilities.py
tests/test_workflows.py
llm_workflow-0.0.22.dist-info/LICENSE
llm_workflow-0.0.22.dist-info/METADATA
llm_workflow-0.0.22.dist-info/WHEEL
llm_workflow-0.0.22.dist-info/top_level.txt
llm_workflow-0.0.22.dist-info/RECORD
