Metadata-Version: 2.1
Name: llm-workflow
Version: 0.0.22
Summary: build LLM workflows
Home-page: https://github.com/shane-kercheval/llm-workflow
Author: Shane Kercheval
Author-email: shane.kercheval@gmail.com
Project-URL: Bug Tracker, https://github.com/shane-kercheval/llm-workflow/issues
Classifier: Programming Language :: Python :: 3
Classifier: License :: OSI Approved :: MIT License
Classifier: Operating System :: OS Independent
Requires-Python: >=3.10
License-File: LICENSE
Requires-Dist: joblib
Requires-Dist: openai
Requires-Dist: pydantic
Requires-Dist: tenacity
Requires-Dist: transformers
Requires-Dist: torch
Requires-Dist: torchvision
Requires-Dist: torchaudio
Requires-Dist: tiktoken
